mps/__init__.py
mps/__main__.py
mps/_base.py
mps/_cache.py
mps/_typing.py
mps/aio/__init__.py
mps/builder.py
mps/cli.py
mps/core/README.md
mps/core/__init__.py
mps/core/config.py
mps/core/constants.py
mps/core/discovery.py
mps/core/errors.py
mps/core/validation.py
mps/ext/__init__.py
mps/fetcher.py
mps/injector.py
mps/integration/__init__.py
mps/integration/_base.py
mps/integration/lang_chain/__init__.py
mps/integration/semantic_kernel/__init__.py
mps/integration/semantic_kernel/_plugins.py
mps/integration/semantic_kernel/plugins/__init__.py
mps/integration/semantic_kernel/plugins/reasoning.py
mps/integration/semantic_kernel/semantic_kernel.py
mps/loader.py
mps/models.py
mps/py.typed
mps/tools/__init__.py
mps/tools/_compiler.py
mps/tools/tools.py
mps/utils/__init__.py
mps/utils/decorators.py
mps/utils/dicttools.py
mps/utils/io.py
mps/utils/miniatures.py
mps/utils/uri.py
mps_engine-0.0.3.dist-info/METADATA
mps_engine-0.0.3.dist-info/WHEEL
mps_engine-0.0.3.dist-info/entry_points.txt
samples/.env.example
samples/__init__.py
samples/configuration.py
samples/context.py
samples/inject.py
samples/meta.py
samples/mps/README.md
samples/mps/ext/configuration/godots-design-philosophy-—-godot-engine-stable-documentation-in-english.md
samples/mps/ext/configuration/short-generator.json
samples/mps/ext/context/.gitkeep
samples/mps/ext/context/biography.txt
samples/mps/ext/context/godots-design-philosophy-—-godot-engine-stable-documentation-in-english.md
samples/mps/ext/context/keep-alive-header-http-mdn.md
samples/mps/ext/preference/latex.txt
samples/mps/ext/preference/programming-language.txt
samples/mps/ext/preference/text-editor.txt
samples/mps/meta/teacher-assistant/system.md
samples/mps/pattern/analyze-mistakes/system.md
samples/mps/pattern/assist-teacher/system.md
samples/mps/pattern/create-quiz/system.md
samples/mps/pattern/translate/system.md
samples/mps/pattern/tutor-student/system.md
samples/mps/strategy/aot.json
samples/mps/strategy/cod.json
samples/mps/strategy/cot.json
samples/mps/strategy/ltm.json
samples/mps/strategy/reflexion.json
samples/mps/strategy/self-consistent.json
mps_engine-0.0.3.dist-info/RECORD
