Metadata-Version: 2.1
Name: mps-engine
Version: 0.0.3
Summary: MPS Engine Python SDK
Author-Email: Mohanad Ghali <mghalix@gmail.com>
License: MIT
Classifier: Intended Audience :: Information Technology
Classifier: Intended Audience :: System Administrators
Classifier: Operating System :: OS Independent
Classifier: Programming Language :: Python :: 3
Classifier: Programming Language :: Python
Classifier: Topic :: Internet
Classifier: Topic :: Software Development :: Libraries :: Application Frameworks
Classifier: Topic :: Software Development :: Libraries :: Python Modules
Classifier: Topic :: Software Development :: Libraries
Classifier: Topic :: Software Development
Classifier: Typing :: Typed
Classifier: Development Status :: 4 - Beta
Classifier: Framework :: Pydantic :: 2
Classifier: Intended Audience :: Developers
Classifier: License :: OSI Approved :: MIT License
Classifier: Programming Language :: Python :: 3 :: Only
Classifier: Programming Language :: Python :: 3.8
Classifier: Programming Language :: Python :: 3.9
Classifier: Programming Language :: Python :: 3.10
Classifier: Programming Language :: Python :: 3.11
Classifier: Programming Language :: Python :: 3.12
Classifier: Programming Language :: Python :: 3.13
Project-URL: Homepage, https://github.com/mghalix/mps
Project-URL: Documentation, https://github.com/mghalix/mps#readme
Project-URL: Issues, https://github.com/mghalix/mps/issues
Project-URL: Respository, https://github.com/mghalix/mps.git
Project-URL: Changelog, https://github.com/mghalix/release-notes/
Requires-Python: >=3.11
Requires-Dist: case-converter>=1.2.0
Requires-Dist: jinja2>=3.1.6
Requires-Dist: loguru>=0.7.3
Requires-Dist: markitdown>=0.1.2
Requires-Dist: pydantic>=2.11.4
Requires-Dist: pydantic-settings>=2.9.1
Provides-Extra: all
Requires-Dist: semantic-kernel>=1.29.0; extra == "all"
Provides-Extra: semantic-kernel
Requires-Dist: semantic-kernel>=1.29.0; extra == "semantic-kernel"
